amotion/__init__.py
amotion/amotion.py
amotion-0.1.10.dist-info/LICENSE
amotion-0.1.10.dist-info/METADATA
amotion-0.1.10.dist-info/WHEEL
amotion-0.1.10.dist-info/top_level.txt
amotion-0.1.10.dist-info/RECORD
