Metadata-Version: 2.2
Name: amotion
Version: 0.1.10
Summary: Adapter for managing the connection, control and monitoring of the HVAC aMotion family family
Author-email: Karel Cavojsky <karel@cavojsky.cz>
Project-URL: Homepage, https://github.com/karelcavojsky/python-amotion
Project-URL: Issues, https://github.com/karelcavojsky/python-amotion/issues
Classifier: Programming Language :: Python :: 3
Classifier: License :: OSI Approved :: MIT License
Classifier: Operating System :: OS Independent
Requires-Python: >=3.8
License-File: LICENSE
Requires-Dist: aiohttp>=3.8.5
